hocon/__init__.py
hocon/__version__.py
hocon/_main.py
hocon/constants.py
hocon/exceptions.py
hocon/py.typed
hocon/strings.py
hocon/unresolved.py
hocon/parser/__init__.py
hocon/parser/_data.py
hocon/parser/_eat.py
hocon/parser/_key.py
hocon/parser/_parser.py
hocon/parser/_quoted_string.py
hocon/parser/_simple_value.py
hocon/parser/_unquoted_string.py
hocon/parser/_value_utils.py
hocon/resolver/__init__.py
hocon/resolver/_lazy_resolver.py
hocon/resolver/_resolver.py
hocon/resolver/_self_reference.py
hocon/resolver/_simple_value.py
hocon/resolver/_substitution.py
hocon/resolver/_substitution_resolver.py
hocon2-0.3.0.dist-info/METADATA
hocon2-0.3.0.dist-info/WHEEL
hocon2-0.3.0.dist-info/licenses/LICENSE
hocon2-0.3.0.dist-info/RECORD
