Metadata-Version: 2.4
Name: hocon2
Version: 0.3.0
Summary: HOCON parser for python
Project-URL: Homepage, https://github.com/myjniak/hocon
Project-URL: Source, https://github.com/myjniak/hocon
Project-URL: Changelog, https://github.com/myjniak/hocon/blob/main/CHANGELOG.md
Author-email: Michał Szajkowski <myjniak@gmail.com>
License-File: LICENSE
Classifier: Intended Audience :: Developers
Classifier: License :: OSI Approved :: MIT License
Classifier: Operating System :: OS Independent
Classifier: Programming Language :: Python :: 3.11
Classifier: Programming Language :: Python :: 3.12
Classifier: Programming Language :: Python :: 3.13
Classifier: Programming Language :: Python :: 3.14
Classifier: Topic :: File Formats
Requires-Python: >=3.11
